{"assets":{"3D698E1DB5ABB990F06E38B159A4B38D":{"type":"texture","index":0,"assetRequest":{"type":"slide","state":"contents","slide":"none"},"url":{"native":"assets\/3FB6ED3F-69A7-41E4-AA8F-E8F0E2F29B51.pdf"},"width":1440,"height":810},"5A4D08F5934EF0F99288E0E566409AA0":{"type":"texture","index":1,"assetRequest":{"type":"slide","state":"contents","slide":"none"},"url":{"native":"assets\/3FB6ED3F-69A7-41E4-AA8F-E8F0E2F29B51.pdf"},"width":1440,"height":810}},"events":[{"effects":[{"beginTime":0,"baseLayer":{"animations":[],"initialState":{"affineTransform":[1,0,0,1,0,0],"masksToBounds":false,"rotation":0,"scale":1,"position":{"pointX":720,"pointY":405},"width":1440,"sublayerTransform":[1,0,0,0,0,1,0,0,0,0,1,0,0,0,0,1],"contentsRect":{"y":0,"x":0,"width":1,"height":1},"opacity":1,"edgeAntialiasingMask":251658240,"height":810,"hidden":false,"anchorPoint":{"pointX":0.5,"pointY":0.5}},"objectID":"0","layers":[{"animations":[],"initialState":{"affineTransform":[1,0,0,1,0,0],"masksToBounds":false,"rotation":0,"scale":1,"position":{"pointX":720,"pointY":405},"width":1440,"sublayerTransform":[1,0,0,0,0,1,0,0,0,0,1,-0.00046677216622367974,0,0,0,1],"contentsRect":{"y":0,"x":0,"width":1,"height":1},"opacity":1,"edgeAntialiasingMask":251658240,"height":810,"hidden":false,"anchorPoint":{"pointX":0.5,"pointY":0.5}},"layers":[{"animations":[],"layers":[],"texturedRectangle":{"isBackgroundTexture":false,"singleTextureOpacity":1,"textureType":0,"textBaseline":0,"textXHeight":0,"isVerticalText":false},"initialState":{"affineTransform":[1,0,0,1,0,0],"masksToBounds":false,"rotation":0,"scale":1,"position":{"pointX":720,"pointY":405},"width":1440,"sublayerTransform":[1,0,0,0,0,1,0,0,0,0,1,0,0,0,0,1],"contentsRect":{"y":0,"x":0,"width":1,"height":1},"opacity":1,"edgeAntialiasingMask":0,"height":810,"hidden":false,"anchorPoint":{"pointX":0.5,"pointY":0.5}},"texture":"5A4D08F5934EF0F99288E0E566409AA0"},{"animations":[{"timeOffset":0,"from":{"scalar":false},"beginTime":0,"repeatCount":0,"fillMode":"both","property":"hidden","autoreverses":false,"duration":0.01,"to":{"scalar":true}}],"layers":[],"texturedRectangle":{"isBackgroundTexture":false,"singleTextureOpacity":1,"textureType":0,"textBaseline":0,"textXHeight":0,"isVerticalText":false},"initialState":{"affineTransform":[1,0,0,1,0,0],"masksToBounds":false,"rotation":0,"scale":1,"position":{"pointX":720,"pointY":405},"width":1440,"sublayerTransform":[1,0,0,0,0,1,0,0,0,0,1,0,0,0,0,1],"contentsRect":{"y":0,"x":0,"width":1,"height":1},"opacity":1,"edgeAntialiasingMask":0,"height":810,"hidden":false,"anchorPoint":{"pointX":0.5,"pointY":0.5}},"texture":"3D698E1DB5ABB990F06E38B159A4B38D"}]}]},"effects":[],"duration":0.01,"type":"transition","name":"none","objectID":"0"}],"automaticPlay":false,"hyperlinks":[],"accessibility":[{"text":"Getting started with OSS","targetRectangle":{"y":333.58755493164062,"x":421.62319946289062,"width":588.9404296875,"height":56.3642578125}},{"text":"logo-futuresync.png","targetRectangle":{"y":10.323081016540527,"x":1113.4857177734375,"width":324.0499267578125,"height":81.591140747070312}}],"baseLayer":{"animations":[],"initialState":{"affineTransform":[1,0,0,1,0,0],"masksToBounds":false,"rotation":0,"scale":1,"position":{"pointX":720,"pointY":405},"width":1440,"sublayerTransform":[1,0,0,0,0,1,0,0,0,0,1,0,0,0,0,1],"contentsRect":{"y":0,"x":0,"width":1,"height":1},"opacity":1,"edgeAntialiasingMask":251658240,"height":810,"hidden":false,"anchorPoint":{"pointX":0.5,"pointY":0.5}},"objectID":"0","layers":[{"animations":[],"initialState":{"affineTransform":[1,0,0,1,0,0],"masksToBounds":false,"rotation":0,"scale":1,"position":{"pointX":720,"pointY":405},"width":1440,"sublayerTransform":[1,0,0,0,0,1,0,0,0,0,1,-0.00046677216622367974,0,0,0,1],"contentsRect":{"y":0,"x":0,"width":1,"height":1},"opacity":1,"edgeAntialiasingMask":251658240,"height":810,"hidden":false,"anchorPoint":{"pointX":0.5,"pointY":0.5}},"layers":[{"animations":[],"layers":[],"texturedRectangle":{"isBackgroundTexture":false,"singleTextureOpacity":1,"textureType":0,"textBaseline":0,"textXHeight":0,"isVerticalText":false},"initialState":{"affineTransform":[1,0,0,1,0,0],"masksToBounds":false,"rotation":0,"scale":1,"position":{"pointX":720,"pointY":405},"width":1440,"sublayerTransform":[1,0,0,0,0,1,0,0,0,0,1,0,0,0,0,1],"contentsRect":{"y":0,"x":0,"width":1,"height":1},"opacity":1,"edgeAntialiasingMask":0,"height":810,"hidden":false,"anchorPoint":{"pointX":0.5,"pointY":0.5}},"texture":"3D698E1DB5ABB990F06E38B159A4B38D"}]}]}}]}